np_data_validator_2/__init__.py
np_data_validator_2/__main__.py
np_data_validator_2/builtins/__init__.py
np_data_validator_2/builtins/processors.py
np_data_validator_2/builtins/utils.py
np_data_validator_2/builtins/validators.py
np_data_validator_2/checksum.py
np_data_validator_2/core.py
np_data_validator_2/dataclasses/__init__.py
np_data_validator_2/lims/__init__.py
np_data_validator_2/lims/queries.py
np_data_validator_2/lims/utils.py
np_data_validator_2/storage.py
np_data_validator_2/transformers/__init__.py
np_data_validator_2/transformers/schemas.py
np_data_validator_2/validation_plan/__init__.py
np_data_validator_2/validation_plan/resolvers.py
np_data_validator_2-0.1.26.dist-info/entry_points.txt
np_data_validator_2-0.1.26.dist-info/LICENSE
np_data_validator_2-0.1.26.dist-info/WHEEL
np_data_validator_2-0.1.26.dist-info/METADATA
np_data_validator_2-0.1.26.dist-info/RECORD
