Metadata-Version: 2.1
Name: np-data-validator-2
Version: 0.1.26
Summary: Awesome `np_data_validator_2` is a Python cli/package created with https://github.com/TezRomacH/python-package-template
Home-page: https://github.com/np_data_validator_2/np_data_validator_2
License: MIT
Author: np_data_validator_2
Author-email: chrism@alleninstitute.org
Requires-Python: >=3.9,<4.0
Classifier: Development Status :: 3 - Alpha
Classifier: Intended Audience :: Developers
Classifier: License :: OSI Approved :: MIT License
Classifier: Operating System :: OS Independent
Classifier: Programming Language :: Python :: 3
Classifier: Programming Language :: Python :: 3.10
Classifier: Programming Language :: Python :: 3.9
Classifier: Topic :: Software Development :: Libraries :: Python Modules
Requires-Dist: marshmallow (>=3.17.0,<4.0.0)
Requires-Dist: numpy (>=1.23.1,<2.0.0)
Requires-Dist: psycopg (>=3.0.16,<4.0.0)
Requires-Dist: pymongo (>=4.2.0,<5.0.0)
Requires-Dist: rich (>=10.14.0,<11.0.0)
Requires-Dist: typer[all] (>=0.4.0,<0.5.0)
Project-URL: Repository, https://github.com/np_data_validator_2/np_data_validator_2
